unireedsolomon/__init__.py
unireedsolomon/_compat.py
unireedsolomon/cff.c
unireedsolomon/cff.cp310-win_amd64.pyd
unireedsolomon/cff.pyx
unireedsolomon/cpolynomial.c
unireedsolomon/cpolynomial.cp310-win_amd64.pyd
unireedsolomon/cpolynomial.pyx
unireedsolomon/ff.py
unireedsolomon/imageencode.py
unireedsolomon/polynomial.py
unireedsolomon/rs.py
unireedsolomon/tests/__init__.py
unireedsolomon/tests/test_cff.py
unireedsolomon/tests/test_cpolynomial.py
unireedsolomon/tests/test_ff.py
unireedsolomon/tests/test_polynomial.py
unireedsolomon/tests/test_rs.py
unireedsolomon-1.0.6.dist-info/LICENSE.txt
unireedsolomon-1.0.6.dist-info/METADATA
unireedsolomon-1.0.6.dist-info/WHEEL
unireedsolomon-1.0.6.dist-info/top_level.txt
unireedsolomon-1.0.6.dist-info/RECORD
