Metadata-Version: 2.1
Name: unireedsolomon
Version: 1.0.6
Summary: Universal errors-and-erasures Reed Solomon codec (error correcting code) in pure Python with extensive documentation and an object-oriented design.
Author-email: Andrew Brown <brownan@gmail.com>, Stephen Karl Larroque <lrq3000@gmail.com>
Maintainer-email: Stephen Karl Larroque <lrq3000@gmail.com>
License: MIT License
Project-URL: Homepage, https://github.com/lrq3000/unireedsolomon
Project-URL: Documentation, https://github.com/lrq3000/unireedsolomon/blob/master/README.rst
Project-URL: Source, https://github.com/lrq3000/unireedsolomon
Project-URL: Tracker, https://github.com/lrq3000/unireedsolomon/issues
Project-URL: Download, https://github.com/lrq3000/unireedsolomon/releases
Keywords: data,protection,correction,recovery,restore,save,data recovery,reed-solomon,error correction code,qr,qr codes,barcodes,error correction,erasure,reed solomon,repair file,network packet
Classifier: Development Status :: 5 - Production/Stable
Classifier: License :: OSI Approved :: MIT License
Classifier: Operating System :: Microsoft :: Windows
Classifier: Operating System :: MacOS :: MacOS X
Classifier: Operating System :: POSIX :: Linux
Classifier: Programming Language :: Python :: 3
Classifier: Programming Language :: Python :: 3.7
Classifier: Programming Language :: Python :: 3.8
Classifier: Programming Language :: Python :: 3.9
Classifier: Programming Language :: Python :: 3.10
Classifier: Programming Language :: Python :: 3.11
Classifier: Programming Language :: Python :: Implementation :: PyPy
Classifier: Programming Language :: Cython
Classifier: Topic :: Communications
Classifier: Topic :: Scientific/Engineering :: Mathematics
Classifier: Topic :: Software Development :: Libraries
Classifier: Topic :: Software Development :: Libraries :: Python Modules
Classifier: Topic :: System :: Archiving
Classifier: Topic :: System :: Archiving :: Backup
Classifier: Topic :: System :: Recovery Tools
Classifier: Topic :: Utilities
Classifier: Intended Audience :: Developers
Classifier: Intended Audience :: Information Technology
Classifier: Intended Audience :: System Administrators
Requires-Python: >=3.7
License-File: LICENSE.txt
Provides-Extra: test
Requires-Dist: pytest ; extra == 'test'
Requires-Dist: pytest-cov ; extra == 'test'
Requires-Dist: coveralls ; extra == 'test'
Requires-Dist: cython (<0.30) ; extra == 'test'
Provides-Extra: testmeta
Requires-Dist: build ; extra == 'testmeta'
Requires-Dist: twine ; extra == 'testmeta'
Requires-Dist: validate-pyproject ; extra == 'testmeta'
Requires-Dist: rstcheck ; extra == 'testmeta'
